{"agent_states": {"BTC_USDT": {"pnl": 0.0, "trades": 0, "wins": 0, "active_pos": null, "last_exit_time": null}, "CHIP_USDT": {"pnl": 0.0, "trades": 0, "wins": 0, "active_pos": null, "last_exit_time": null}, "XAUT_USDT": {"pnl": 0.0, "trades": 0, "wins": 0, "active_pos": null, "last_exit_time": null}, "SOL_USDT": {"pnl": 0.0, "trades": 0, "wins": 0, "active_pos": null, "last_exit_time": null}, "ETH_USDT": {"pnl": 0.0, "trades": 0, "wins": 0, "active_pos": null, "last_exit_time": null}, "POWER_USDT": {"pnl": 0.0, "trades": 0, "wins": 0, "active_pos": null, "last_exit_time": null}, "SPK_USDT": {"pnl": 0.0, "trades": 0, "wins": 0, "active_pos": null, "last_exit_time": null}, "UKOIL_USDT": {"pnl": 0.0, "trades": 0, "wins": 0, "active_pos": {"entry_price": 100.438, "side": "SHORT", "leverage": 10, "size": 1000, "timestamp": "23.04.2026 23:46:08", "entry_time_raw": "2026-04-23T20:46:08.055514", "tp": 95.91829, "sl": 102.94895, "indicators": "RSI:55, MACD+, BB:0.76, EMA\u2191", "unrealized_pnl": 0.0, "current_price": 100.438}, "last_exit_time": null}, "SILVER_USDT": {"pnl": 0.0, "trades": 0, "wins": 0, "active_pos": null, "last_exit_time": null}, "USOIL_USDT": {"pnl": 0.0, "trades": 0, "wins": 0, "active_pos": {"entry_price": 96.815, "side": "SHORT", "leverage": 10, "size": 1000, "timestamp": "23.04.2026 23:46:08", "entry_time_raw": "2026-04-23T20:46:08.284255", "tp": 92.458325, "sl": 99.235375, "indicators": "RSI:51, MACD+, BB:0.71, EMA\u2191", "unrealized_pnl": 0.0, "current_price": 96.815}, "last_exit_time": null}, "SUI_USDT": {"pnl": 0.0, "trades": 0, "wins": 0, "active_pos": null, "last_exit_time": null}, "UB_USDT": {"pnl": 0.0, "trades": 0, "wins": 0, "active_pos": {"entry_price": 0.05211, "side": "SHORT", "leverage": 10, "size": 1000, "timestamp": "23.04.2026 23:46:09", "entry_time_raw": "2026-04-23T20:46:09.417635", "tp": 0.04976505, "sl": 0.05341275, "indicators": "RSI:60, MACD+, BB:0.57, EMA\u2191", "unrealized_pnl": 0.0, "current_price": 0.05211}, "last_exit_time": null}, "RAVE_USDT": {"pnl": 0.0, "trades": 0, "wins": 0, "active_pos": null, "last_exit_time": null}, "SIREN_USDT": {"pnl": 0.0, "trades": 0, "wins": 0, "active_pos": null, "last_exit_time": null}, "ORDI_USDT": {"pnl": 0.0, "trades": 0, "wins": 0, "active_pos": null, "last_exit_time": null}, "ZEC_USDT": {"pnl": 0.0, "trades": 0, "wins": 0, "active_pos": null, "last_exit_time": null}, "XRP_USDT": {"pnl": 0.0, "trades": 0, "wins": 0, "active_pos": null, "last_exit_time": null}, "MOVR_USDT": {"pnl": 0.0, "trades": 0, "wins": 0, "active_pos": null, "last_exit_time": null}, "TAO_USDT": {"pnl": 0.0, "trades": 0, "wins": 0, "active_pos": null, "last_exit_time": null}, "ASTEROID_USDT": {"pnl": 0.0, "trades": 0, "wins": 0, "active_pos": null, "last_exit_time": null}, "LINK_USDT": {"pnl": 0.0, "trades": 0, "wins": 0, "active_pos": null, "last_exit_time": null}, "MAGMA_USDT": {"pnl": 0.0, "trades": 0, "wins": 0, "active_pos": null, "last_exit_time": null}, "OPG_USDT": {"pnl": 0.0, "trades": 0, "wins": 0, "active_pos": null, "last_exit_time": null}, "HYPE_USDT": {"pnl": 0.0, "trades": 0, "wins": 0, "active_pos": null, "last_exit_time": null}, "PIPPIN_USDT": {"pnl": 0.0, "trades": 0, "wins": 0, "active_pos": null, "last_exit_time": null}, "DOGE_USDT": {"pnl": 0.0, "trades": 0, "wins": 0, "active_pos": null, "last_exit_time": null}, "BSB_USDT": {"pnl": 0.0, "trades": 0, "wins": 0, "active_pos": null, "last_exit_time": null}, "RIVER_USDT": {"pnl": 0.0, "trades": 0, "wins": 0, "active_pos": null, "last_exit_time": null}, "ADA_USDT": {"pnl": 0.0, "trades": 0, "wins": 0, "active_pos": null, "last_exit_time": null}, "TAC_USDT": {"pnl": 0.0, "trades": 0, "wins": 0, "active_pos": null, "last_exit_time": null}, "Q_USDT": {"pnl": 0.0, "trades": 0, "wins": 0, "active_pos": null, "last_exit_time": null}, "CORE_USDT": {"pnl": 0.0, "trades": 0, "wins": 0, "active_pos": null, "last_exit_time": null}, "VELVET_USDT": {"pnl": 0.0, "trades": 0, "wins": 0, "active_pos": null, "last_exit_time": null}, "BB_USDT": {"pnl": 0.0, "trades": 0, "wins": 0, "active_pos": null, "last_exit_time": null}, "AAVE_USDT": {"pnl": 0.0, "trades": 0, "wins": 0, "active_pos": null, "last_exit_time": null}, "PEPE_USDT": {"pnl": 0.0, "trades": 0, "wins": 0, "active_pos": null, "last_exit_time": null}, "PENGU_USDT": {"pnl": 0.0, "trades": 0, "wins": 0, "active_pos": null, "last_exit_time": null}, "ENA_USDT": {"pnl": 0.0, "trades": 0, "wins": 0, "active_pos": null, "last_exit_time": null}, "CYPR_USDT": {"pnl": 0.0, "trades": 0, "wins": 0, "active_pos": null, "last_exit_time": null}, "STRK_USDT": {"pnl": 0.0, "trades": 0, "wins": 0, "active_pos": null, "last_exit_time": null}, "BAS_USDT": {"pnl": 0.0, "trades": 0, "wins": 0, "active_pos": {"entry_price": 0.017021, "side": "SHORT", "leverage": 10, "size": 1000, "timestamp": "23.04.2026 23:46:15", "entry_time_raw": "2026-04-23T20:46:15.083609", "tp": 0.016255055, "sl": 0.017446525, "indicators": "RSI:55, MACD-, BB:0.66, EMA\u2191", "unrealized_pnl": 0.0, "current_price": 0.017021}, "last_exit_time": null}, "SKYAI_USDT": {"pnl": 0.0, "trades": 0, "wins": 0, "active_pos": null, "last_exit_time": null}, "ON_USDT": {"pnl": 0.0, "trades": 0, "wins": 0, "active_pos": null, "last_exit_time": null}, "GENIUS_USDT": {"pnl": 0.0, "trades": 0, "wins": 0, "active_pos": null, "last_exit_time": null}, "BNB_USDT": {"pnl": 0.0, "trades": 0, "wins": 0, "active_pos": null, "last_exit_time": null}, "TRADOOR_USDT": {"pnl": 0.0, "trades": 0, "wins": 0, "active_pos": null, "last_exit_time": null}, "KAT_USDT": {"pnl": 0.0, "trades": 0, "wins": 0, "active_pos": null, "last_exit_time": null}, "LAB_USDT": {"pnl": 0.0, "trades": 0, "wins": 0, "active_pos": null, "last_exit_time": null}, "WIF_USDT": {"pnl": 0.0, "trades": 0, "wins": 0, "active_pos": null, "last_exit_time": null}, "AVAX_USDT": {"pnl": 0.0, "trades": 0, "wins": 0, "active_pos": null, "last_exit_time": null}, "H_USDT": {"pnl": 0.0, "trades": 0, "wins": 0, "active_pos": null, "last_exit_time": null}, "HIGH_USDT": {"pnl": 0.0, "trades": 0, "wins": 0, "active_pos": null, "last_exit_time": null}, "WLD_USDT": {"pnl": 0.0, "trades": 0, "wins": 0, "active_pos": null, "last_exit_time": null}, "FARTCOIN_USDT": {"pnl": 0.0, "trades": 0, "wins": 0, "active_pos": null, "last_exit_time": null}, "M_USDT": {"pnl": 0.0, "trades": 0, "wins": 0, "active_pos": null, "last_exit_time": null}, "LYN_USDT": {"pnl": 0.0, "trades": 0, "wins": 0, "active_pos": null, "last_exit_time": null}, "PIEVERSE_USDT": {"pnl": 0.0, "trades": 0, "wins": 0, "active_pos": null, "last_exit_time": null}, "BASED_USDT": {"pnl": 0.0, "trades": 0, "wins": 0, "active_pos": null, "last_exit_time": null}, "GUN_USDT": {"pnl": 0.0, "trades": 0, "wins": 0, "active_pos": null, "last_exit_time": null}, "DOT_USDT": {"pnl": 0.0, "trades": 0, "wins": 0, "active_pos": null, "last_exit_time": null}}, "trade_history": [], "portfolio": {"capital": 99997.59999999998, "total_fees": 2.4, "initial_capital": 100000.0}, "timestamp": "2026-04-23T20:46:18.081065"}